livemasjid/__init__.py
livemasjid/livemasjid.py
livemasjid-0.1.2.dist-info/WHEEL
livemasjid-0.1.2.dist-info/METADATA
livemasjid-0.1.2.dist-info/RECORD
