Metadata-Version: 2.1
Name: livemasjid
Version: 0.1.2
Summary: This package provides a pythonic interface to subscribe to updates from Livemasjid as well as to get sthe current status of Livemasjid streams.
Author: Yusuff Lockhat
Author-email: 45769466+lockhaty@users.noreply.github.com
Requires-Python: >=3.6,<4.0
Classifier: Programming Language :: Python :: 3
Classifier: Programming Language :: Python :: 3.6
Classifier: Programming Language :: Python :: 3.7
Classifier: Programming Language :: Python :: 3.8
Classifier: Programming Language :: Python :: 3.9
Requires-Dist: paho-mqtt (>=1.5.1,<2.0.0)
Requires-Dist: requests (>=2.26.0,<3.0.0)
Requires-Dist: websocket (>=0.2.1,<0.3.0)
